{
    "keep": {
        "days": true,
        "amount": 14
    },
    "auditLog": "E:\\Projects\\sanil\\tr-web-portal-server\\logs\\winston\\successes\\.7c76ab7a2b26e1dc21acc609735ca63cbf3f46dd-audit.json",
    "files": [
        {
            "date": 1735845756057,
            "name": "E:\\Projects\\sanil\\tr-web-portal-server\\logs\\winston\\successes\\phu-2025-03-01-01-success.log",
            "hash": "cae4d8c0c959b13932d25485ca0d8fb437ed69279ed80745b6f51715320c88f7"
        },
        {
            "date": 1736396405873,
            "name": "E:\\Projects\\sanil\\tr-web-portal-server\\logs\\winston\\successes\\phu-2025-09-01-10-success.log",
            "hash": "190e0ac51f59bb4753df128fe5a1e0035c5ac7aec52870a1bdd17c79a0c8a82c"
        },
        {
            "date": 1736399312062,
            "name": "E:\\Projects\\sanil\\tr-web-portal-server\\logs\\winston\\successes\\phu-2025-09-01-11-success.log",
            "hash": "47b059c5ec195a55f43d91b9bfcd1801a4abaa345a89f095c7e4739de53a26a6"
        },
        {
            "date": 1736450630993,
            "name": "E:\\Projects\\sanil\\tr-web-portal-server\\logs\\winston\\successes\\phu-2025-10-01-01-success.log",
            "hash": "364171db9ccb27e47cfd9ca08c679d70409e618a8bd1dbbfaec8da5e3260947b"
        },
        {
            "date": 1736453933180,
            "name": "E:\\Projects\\sanil\\tr-web-portal-server\\logs\\winston\\successes\\phu-2025-10-01-02-success.log",
            "hash": "f512a3adbea6fe7e51c3b21c53b226fecd46badec662974c656d18db3f2ca71c"
        },
        {
            "date": 1736456500745,
            "name": "E:\\Projects\\sanil\\tr-web-portal-server\\logs\\winston\\successes\\phu-2025-10-01-03-success.log",
            "hash": "5863e8708dbcd156e53bc3175956d81a8c64c687c8c5e9d5bc8f11eefc9794fd"
        },
        {
            "date": 1736469021325,
            "name": "E:\\Projects\\sanil\\tr-web-portal-server\\logs\\winston\\successes\\phu-2025-10-01-06-success.log",
            "hash": "96379f8bf999f74cd4d30430e4f054667f18f6f164f2737149a06f47c2ca9b57"
        },
        {
            "date": 1736502793795,
            "name": "E:\\Projects\\sanil\\tr-web-portal-server\\logs\\winston\\successes\\phu-2025-10-01-15-success.log",
            "hash": "05f37f259693c7689701a19f6a24ab7449638f6e6093cd26714995ec5426d1e9"
        },
        {
            "date": 1736524253952,
            "name": "E:\\Projects\\sanil\\tr-web-portal-server\\logs\\winston\\successes\\phu-2025-10-01-21-success.log",
            "hash": "dd97fdaf53fa525fcbff81d82f53119f21b628067f4e39f3939c7e9f04dc3f99"
        },
        {
            "date": 1736578920493,
            "name": "E:\\Projects\\sanil\\tr-web-portal-server\\logs\\winston\\successes\\phu-2025-11-01-13-success.log",
            "hash": "0172e68de4411e20d3cd37bb6b7bcfb53669bfdd886e1740a628da70900ace2b"
        },
        {
            "date": 1736687782646,
            "name": "E:\\Projects\\sanil\\tr-web-portal-server\\logs\\winston\\successes\\phu-2025-12-01-19-success.log",
            "hash": "b60a94f5c24d5a98c5f7f2591963f1ed90709ee550a09b65a12ee8022cb6080c"
        },
        {
            "date": 1736690616367,
            "name": "E:\\Projects\\sanil\\tr-web-portal-server\\logs\\winston\\successes\\phu-2025-12-01-20-success.log",
            "hash": "40cc596f0b17195e9ed47d7c88fc718ea61bbc07d27f50b6d0dbf674a1484ff9"
        },
        {
            "date": 1736694028098,
            "name": "E:\\Projects\\sanil\\tr-web-portal-server\\logs\\winston\\successes\\phu-2025-12-01-21-success.log",
            "hash": "2d7e90751fb170ec740b49986d981b7ba40c3c6103a4545c117c7b230f1caf07"
        },
        {
            "date": 1736697885115,
            "name": "E:\\Projects\\sanil\\tr-web-portal-server\\logs\\winston\\successes\\phu-2025-12-01-22-success.log",
            "hash": "8b1cc368868945538040fd493014dda76ddc015c728373d55302523dc3b8d8e9"
        },
        {
            "date": 1736701236563,
            "name": "E:\\Projects\\sanil\\tr-web-portal-server\\logs\\winston\\successes\\phu-2025-12-01-23-success.log",
            "hash": "53342b112e4b5323a40a5ff6b4d1050a2b55539268042fc624c3179dc79b68e2"
        },
        {
            "date": 1736706469538,
            "name": "E:\\Projects\\sanil\\tr-web-portal-server\\logs\\winston\\successes\\phu-2025-13-01-00-success.log",
            "hash": "74cce4705b261e38d844ebbab12b6f85064a5710f05569bcbbdc71fa28edad81"
        },
        {
            "date": 1736710926144,
            "name": "E:\\Projects\\sanil\\tr-web-portal-server\\logs\\winston\\successes\\phu-2025-13-01-01-success.log",
            "hash": "7ebe8abbf30e34acc67f49ca4aa54ff63296917e9617bbbe31c8455d0b396a24"
        },
        {
            "date": 1736712011885,
            "name": "E:\\Projects\\sanil\\tr-web-portal-server\\logs\\winston\\successes\\phu-2025-13-01-02-success.log",
            "hash": "f4c62857980675b02fb09f30214e260e7744075a3caf7687bada7b6daf7cf706"
        }
    ],
    "hashType": "sha256"
}